tapipy_tapisservice/__init__.py
tapipy_tapisservice/auth.py
tapipy_tapisservice/config.py
tapipy_tapisservice/configschema.json
tapipy_tapisservice/errors.py
tapipy_tapisservice/logs.py
tapipy_tapisservice/tapisdjango/__init__.py
tapipy_tapisservice/tapisfastapi/__init__.py
tapipy_tapisservice/tapisflask/__init__.py
tapipy_tapisservice/tapisflask/auth.py
tapipy_tapisservice/tapisflask/resources.py
tapipy_tapisservice/tapisflask/utils.py
tapipy_tapisservice/tenants.py
tapipy_tapisservice/utils.py
tapipy_tapisservice-1.1.0.dist-info/WHEEL
tapipy_tapisservice-1.1.0.dist-info/METADATA
tapipy_tapisservice-1.1.0.dist-info/RECORD
